kuling/__init__.py
kuling/copy.py
kuling/delete.py
kuling/find.py
kuling/move.py
kuling-1.0.2.dist-info/licenses/LICENSE
kuling-1.0.2.dist-info/METADATA
kuling-1.0.2.dist-info/WHEEL
kuling-1.0.2.dist-info/top_level.txt
kuling-1.0.2.dist-info/RECORD
