Metadata-Version: 2.4
Name: kuling
Version: 1.0.2
Summary: Move files around
Author-email: Erik Bremstedt <erik@bremstedt.se>
Project-URL: Homepage, https://github.com/ebremstedt/kuling
Project-URL: Issues, https://github.com/ebremstedt/kuling/issues
Classifier: Programming Language :: Python :: 3
Classifier: License :: OSI Approved :: MIT License
Classifier: Operating System :: OS Independent
Requires-Python: >=3.10
License-File: LICENSE
Dynamic: license-file
